fastapi_auth/__init__.py
fastapi_auth/__main__.py
fastapi_auth/consts.py
fastapi_auth/exceptions.py
fastapi_auth/fastapi_auth.py
fastapi_auth/hasher.py
fastapi_auth/jwt.py
fastapi_auth/permissions.py
fastapi_auth/authenticators/__init__.py
fastapi_auth/authenticators/base.py
fastapi_auth/backends/__init__.py
fastapi_auth/backends/backend.py
fastapi_auth/backends/base.py
fastapi_auth/filters/__init__.py
fastapi_auth/filters/base.py
fastapi_auth/filters/ordering_filter.py
fastapi_auth/filters/search_filter.py
fastapi_auth/managers/__init__.py
fastapi_auth/managers/base.py
fastapi_auth/managers/manager.py
fastapi_auth/models/__init__.py
fastapi_auth/models/model.py
fastapi_auth/models/token.py
fastapi_auth/models/user.py
fastapi_auth/pagination/__init__.py
fastapi_auth/pagination/base.py
fastapi_auth/pagination/limit_pagination.py
fastapi_auth/pagination/page.py
fastapi_auth/pagination/page_pagination.py
fastapi_auth/repositories/__init__.py
fastapi_auth/repositories/base.py
fastapi_auth/schemas/__init__.py
fastapi_auth/schemas/default_schemas.py
fastapi_auth/serializers/__init__.py
fastapi_auth/serializers/base.py
fastapi_auth/serializers/serializers.py
fastapi_auth/serializers/sqlalchemy/__init__.py
fastapi_auth/serializers/sqlalchemy/serializers.py
fastapi_auth/serializers/tortoise/__init__.py
fastapi_auth/serializers/tortoise/serializers.py
fastapi_auth/signals/__init__.py
fastapi_auth/signals/signal.py
fastapi_auth/sqlalchemy_models/__init__.py
fastapi_auth/strategies/__init__.py
fastapi_auth/strategies/base.py
fastapi_auth/strategies/db.py
fastapi_auth/strategies/jwt.py
fastapi_auth/tortoise_models/__init__.py
fastapi_auth/utils/__init__.py
fastapi_auth/utils/command_utils.py
fastapi_auth/utils/utils.py
auth_fastapi-1.0.3.dist-info/METADATA
auth_fastapi-1.0.3.dist-info/WHEEL
auth_fastapi-1.0.3.dist-info/entry_points.txt
auth_fastapi-1.0.3.dist-info/RECORD
